<?xml version="1.0" ?><FASTConfiguration _type="null">
	<DefaultReaderConfiguration _type="null" autoStart="true" description="vsftpd xferlog" logInterval="1" logLocation="/var/log/xferlog" logManagementOutput="10.254.10.18" logManagementPort="10101" logStartPoint="-1" logType="BufferedReader" node="manager,spop" readerName="vsftpxfer" readerOutput="Alert" stateVars="logStartPoint,readerName" toolId="vsftpxfer" toolType="File Transfer and Sharing" version="$Revision: #4 $" vendor="" fullDescription="" categoryTags="">
		<file _type="null" attributeName="logLocation" enabled="true" formatRule="" formatted="false" labelText="Log File:" preferredOrder="1" toolTipText="Directory or path to read from" visible="true"></file>
		<string _type="null" attributeName="logManagementOutput" enabled="false" formatRule="" formatted="false" guiVersion="4" labelText="nDepth Host:" preferredOrder="91" toolTipText="Hostname of the nDepth appliance to receive log data" visible="false"></string>
		<integer _type="null" attributeName="logManagementPort" enabled="false" guiVersion="4" labelText="nDepth Port:" maxValue="32000" minValue="0" preferredOrder="92" toolTipText="Port number of the nDepth appliance to receive log data" visible="false"></integer>
		<select _type="null" attributeName="readerOutput" enabled="false" guiVersion="4" labelText="Output:" preferredOrder="90" selectItems="Alert;InDepth;Alert, InDepth" toolTipText="Data routing (normalized alerts to Manager and/or raw data to nDepth)" visible="false"></select>
		<integer _type="null" attributeName="logInterval" enabled="true" labelText="Sleep Time:" maxValue="3660" minValue="1" preferredOrder="97" toolTipText="Number of seconds between log reads" visible="true"></integer>
		<string _type="null" attributeName="version" enabled="false" formatRule="" formatted="false" labelText="Tool Version:" preferredOrder="99" toolTipText="Tool version" visible="true"></string>
		<string _type="null" attributeName="toolId" enabled="false" formatRule="" formatted="false" labelText="Wrapper Name:" preferredOrder="98" toolTipText="Tool Identifier" visible="true"></string>
	</DefaultReaderConfiguration>
	<FastToolId _type="null" description="vsftpd xferlog" id="vsftpxfer" version="8" version_type="int">
		<FastPattern _type="null" alertName="FileTransferTrafficAudit" description="FileTransferTrafficAudit: xferlog" matcher="\w{3} (\w{3} +\d{1,2} \d{2}:\d{2}:\d{2} \d{4}) (\d+) ([-\w.]+) (\d+) (.+) ([ab]) ([CUT_]) ([io]) ([agr]) (\S+) ([-\w]+) ([01]) (\S+) ([ci]).*" pattern="\w{3} \w{3} +\d{1,2} \d{2}:\d{2}:\d{2} \d{4} \d+ [-\w.]+ \d+ .+ [ab] [CUT_] [io] [agr] \S+ [-\w]+ [01] \S+ [ci]" version="7" version_type="int">
			<FastField _type="null" defaultValue="$5" fieldName="EventInfo" type="1" type_type="int" version="3" version_type="int">
				<FastFormatter _type="null" condition="i" description="incoming" format="$11 incoming file &quot;$5&quot; from &quot;$3&quot;" matcherInput="$8" version="2" version_type="int"></FastFormatter>
				<FastFormatter _type="null" condition="o" description="outgoing" format="$11 outgoing file &quot;$5&quot; to &quot;$3&quot;" matcherInput="$8" version="2" version_type="int"></FastFormatter>
			</FastField>
			<FastField _type="null" defaultValue="" fieldName="DetectionTime" type="4" type_type="int" version="2" version_type="int">
				<FastFormatter _type="null" condition="Jan (\d{2}) (\d{2}:\d{2}:\d{2}) (\d{4})" description="2day-Jan" format="$18-01-$16 $17" matcherInput="$1" version="1" version_type="int"></FastFormatter>
				<FastFormatter _type="null" condition="Feb (\d{2}) (\d{2}:\d{2}:\d{2}) (\d{4})" description="2day-Feb" format="$18-02-$16 $17" matcherInput="$1" version="1" version_type="int"></FastFormatter>
				<FastFormatter _type="null" condition="Mar (\d{2}) (\d{2}:\d{2}:\d{2}) (\d{4})" description="2day-Mar" format="$18-03-$16 $17" matcherInput="$1" version="1" version_type="int"></FastFormatter>
				<FastFormatter _type="null" condition="Apr (\d{2}) (\d{2}:\d{2}:\d{2}) (\d{4})" description="2day-Apr" format="$18-04-$16 $17" matcherInput="$1" version="1" version_type="int"></FastFormatter>
				<FastFormatter _type="null" condition="May (\d{2}) (\d{2}:\d{2}:\d{2}) (\d{4})" description="2day-May" format="$18-05-$16 $17" matcherInput="$1" version="1" version_type="int"></FastFormatter>
				<FastFormatter _type="null" condition="Jun (\d{2}) (\d{2}:\d{2}:\d{2}) (\d{4})" description="2day-Jun" format="$18-06-$16 $17" matcherInput="$1" version="1" version_type="int"></FastFormatter>
				<FastFormatter _type="null" condition="Jul (\d{2}) (\d{2}:\d{2}:\d{2}) (\d{4})" description="2day-Jul" format="$18-07-$16 $17" matcherInput="$1" version="1" version_type="int"></FastFormatter>
				<FastFormatter _type="null" condition="Aug (\d{2}) (\d{2}:\d{2}:\d{2}) (\d{4})" description="2day-Aug" format="$18-08-$16 $17" matcherInput="$1" version="1" version_type="int"></FastFormatter>
				<FastFormatter _type="null" condition="Sep (\d{2}) (\d{2}:\d{2}:\d{2}) (\d{4})" description="2day-Sep" format="$18-09-$16 $17" matcherInput="$1" version="1" version_type="int"></FastFormatter>
				<FastFormatter _type="null" condition="Oct (\d{2}) (\d{2}:\d{2}:\d{2}) (\d{4})" description="2day-Oct" format="$18-10-$16 $17" matcherInput="$1" version="1" version_type="int"></FastFormatter>
				<FastFormatter _type="null" condition="Nov (\d{2}) (\d{2}:\d{2}:\d{2}) (\d{4})" description="2day-Nov" format="$18-11-$16 $17" matcherInput="$1" version="1" version_type="int"></FastFormatter>
				<FastFormatter _type="null" condition="Dec (\d{2}) (\d{2}:\d{2}:\d{2}) (\d{4})" description="2day-Dec" format="$18-12-$16 $17" matcherInput="$1" version="1" version_type="int"></FastFormatter>
				<FastFormatter _type="null" condition="Jan +(\d) (\d{2}:\d{2}:\d{2}) (\d{4})" description="1day-Jan" format="$18-01-0$16 $17" matcherInput="$1" version="1" version_type="int"></FastFormatter>
				<FastFormatter _type="null" condition="Feb +(\d) (\d{2}:\d{2}:\d{2}) (\d{4})" description="1day-Feb" format="$18-02-0$16 $17" matcherInput="$1" version="1" version_type="int"></FastFormatter>
				<FastFormatter _type="null" condition="Mar +(\d) (\d{2}:\d{2}:\d{2}) (\d{4})" description="1day-Mar" format="$18-03-0$16 $17" matcherInput="$1" version="1" version_type="int"></FastFormatter>
				<FastFormatter _type="null" condition="Apr +(\d) (\d{2}:\d{2}:\d{2}) (\d{4})" description="1day-Apr" format="$18-04-0$16 $17" matcherInput="$1" version="1" version_type="int"></FastFormatter>
				<FastFormatter _type="null" condition="May +(\d) (\d{2}:\d{2}:\d{2}) (\d{4})" description="1day-May" format="$18-05-0$16 $17" matcherInput="$1" version="1" version_type="int"></FastFormatter>
				<FastFormatter _type="null" condition="Jun +(\d) (\d{2}:\d{2}:\d{2}) (\d{4})" description="1day-Jun" format="$18-06-0$16 $17" matcherInput="$1" version="1" version_type="int"></FastFormatter>
				<FastFormatter _type="null" condition="Jul +(\d) (\d{2}:\d{2}:\d{2}) (\d{4})" description="1day-Jul" format="$18-07-0$16 $17" matcherInput="$1" version="1" version_type="int"></FastFormatter>
				<FastFormatter _type="null" condition="Aug +(\d) (\d{2}:\d{2}:\d{2}) (\d{4})" description="1day-Aug" format="$18-08-0$16 $17" matcherInput="$1" version="1" version_type="int"></FastFormatter>
				<FastFormatter _type="null" condition="Sep +(\d) (\d{2}:\d{2}:\d{2}) (\d{4})" description="1day-Sep" format="$18-09-0$16 $17" matcherInput="$1" version="1" version_type="int"></FastFormatter>
				<FastFormatter _type="null" condition="Oct +(\d) (\d{2}:\d{2}:\d{2}) (\d{4})" description="1day-Oct" format="$18-10-0$16 $17" matcherInput="$1" version="1" version_type="int"></FastFormatter>
				<FastFormatter _type="null" condition="Nov +(\d) (\d{2}:\d{2}:\d{2}) (\d{4})" description="1day-Nov" format="$18-11-0$16 $17" matcherInput="$1" version="1" version_type="int"></FastFormatter>
				<FastFormatter _type="null" condition="Dec +(\d) (\d{2}:\d{2}:\d{2}) (\d{4})" description="1day-Dec" format="$18-12-0$16 $17" matcherInput="$1" version="1" version_type="int"></FastFormatter>
			</FastField>
			<FastField _type="null" defaultValue="1" fieldName="ProviderSID" type="1" type_type="int" version="1" version_type="int"></FastField>
			<FastField _type="null" defaultValue="" fieldName="ExtraneousInfo" type="1" type_type="int" version="1" version_type="int">
				<FastFormatter _type="null" condition="\*,a,T,a,0,c" description="info=*,a,T,a,0,c" format="Username: &quot;$10&quot;, Type: Ascii, Action: Archived, Mode: Anonymous, Auth_Used: None, Status: Complete" matcherInput="$13,$6,$7,$9,$12,$14" version="1" version_type="int"></FastFormatter>
				<FastFormatter _type="null" condition="\*,a,T,a,0,i" description="info=*,a,T,a,0,i" format="Username: &quot;$10&quot;, Type: Ascii, Action: Archived, Mode: Anonymous, Auth_Used: None, Status: Incomplete" matcherInput="$13,$6,$7,$9,$12,$14" version="1" version_type="int"></FastFormatter>
				<FastFormatter _type="null" condition="\*,a,T,a,1,c" description="info=*,a,T,a,1,c" format="Username: &quot;$10&quot;, Type: Ascii, Action: Archived, Mode: Anonymous, Auth_Used: RFC931, Status: Complete" matcherInput="$13,$6,$7,$9,$12,$14" version="1" version_type="int"></FastFormatter>
				<FastFormatter _type="null" condition="\*,a,T,a,1,i" description="info=*,a,T,a,1,i" format="Username: &quot;$10&quot;, Type: Ascii, Action: Archived, Mode: Anonymous, Auth_Used: RFC931, Status: Incomplete" matcherInput="$13,$6,$7,$9,$12,$14" version="1" version_type="int"></FastFormatter>
				<FastFormatter _type="null" condition="\*,a,T,g,0,c" description="info=*,a,T,g,0,c" format="Username: &quot;$10&quot;, Type: Ascii, Action: Archived, Mode: Guest, Auth_Used: None, Status: Complete" matcherInput="$13,$6,$7,$9,$12,$14" version="1" version_type="int"></FastFormatter>
				<FastFormatter _type="null" condition="\*,a,T,g,0,i" description="info=*,a,T,g,0,i" format="Username: &quot;$10&quot;, Type: Ascii, Action: Archived, Mode: Guest, Auth_Used: None, Status: Incomplete" matcherInput="$13,$6,$7,$9,$12,$14" version="1" version_type="int"></FastFormatter>
				<FastFormatter _type="null" condition="\*,a,T,g,1,c" description="info=*,a,T,g,1,c" format="Username: &quot;$10&quot;, Type: Ascii, Action: Archived, Mode: Guest, Auth_Used: RFC931, Status: Complete" matcherInput="$13,$6,$7,$9,$12,$14" version="1" version_type="int"></FastFormatter>
				<FastFormatter _type="null" condition="\*,a,T,g,1,i" description="info=*,a,T,g,1,i" format="Username: &quot;$10&quot;, Type: Ascii, Action: Archived, Mode: Guest, Auth_Used: RFC931, Status: Incomplete" matcherInput="$13,$6,$7,$9,$12,$14" version="1" version_type="int"></FastFormatter>
				<FastFormatter _type="null" condition="\*,a,T,r,0,c" description="info=*,a,T,r,0,c" format="Username: &quot;$10&quot;, Type: Ascii, Action: Archived, Mode: Local, Auth_Used: None, Status: Complete" matcherInput="$13,$6,$7,$9,$12,$14" version="1" version_type="int"></FastFormatter>
				<FastFormatter _type="null" condition="\*,a,T,r,0,i" description="info=*,a,T,r,0,i" format="Username: &quot;$10&quot;, Type: Ascii, Action: Archived, Mode: Local, Auth_Used: None, Status: Incomplete" matcherInput="$13,$6,$7,$9,$12,$14" version="1" version_type="int"></FastFormatter>
				<FastFormatter _type="null" condition="\*,a,T,r,1,c" description="info=*,a,T,r,1,c" format="Username: &quot;$10&quot;, Type: Ascii, Action: Archived, Mode: Local, Auth_Used: RFC931, Status: Complete" matcherInput="$13,$6,$7,$9,$12,$14" version="1" version_type="int"></FastFormatter>
				<FastFormatter _type="null" condition="\*,a,T,r,1,i" description="info=*,a,T,r,1,i" format="Username: &quot;$10&quot;, Type: Ascii, Action: Archived, Mode: Local, Auth_Used: RFC931, Status: Incomplete" matcherInput="$13,$6,$7,$9,$12,$14" version="1" version_type="int"></FastFormatter>
				<FastFormatter _type="null" condition="\*,a,C,a,0,c" description="info=*,a,C,a,0,c" format="Username: &quot;$10&quot;, Type: Ascii, Action: Compressed, Mode: Anonymous, Auth_Used: None, Status: Complete" matcherInput="$13,$6,$7,$9,$12,$14" version="1" version_type="int"></FastFormatter>
				<FastFormatter _type="null" condition="\*,a,C,a,0,i" description="info=*,a,C,a,0,i" format="Username: &quot;$10&quot;, Type: Ascii, Action: Compressed, Mode: Anonymous, Auth_Used: None, Status: Incomplete" matcherInput="$13,$6,$7,$9,$12,$14" version="1" version_type="int"></FastFormatter>
				<FastFormatter _type="null" condition="\*,a,C,a,1,c" description="info=*,a,C,a,1,c" format="Username: &quot;$10&quot;, Type: Ascii, Action: Compressed, Mode: Anonymous, Auth_Used: RFC931, Status: Complete" matcherInput="$13,$6,$7,$9,$12,$14" version="1" version_type="int"></FastFormatter>
				<FastFormatter _type="null" condition="\*,a,C,a,1,i" description="info=*,a,C,a,1,i" format="Username: &quot;$10&quot;, Type: Ascii, Action: Compressed, Mode: Anonymous, Auth_Used: RFC931, Status: Incomplete" matcherInput="$13,$6,$7,$9,$12,$14" version="1" version_type="int"></FastFormatter>
				<FastFormatter _type="null" condition="\*,a,C,g,0,c" description="info=*,a,C,g,0,c" format="Username: &quot;$10&quot;, Type: Ascii, Action: Compressed, Mode: Guest, Auth_Used: None, Status: Complete" matcherInput="$13,$6,$7,$9,$12,$14" version="1" version_type="int"></FastFormatter>
				<FastFormatter _type="null" condition="\*,a,C,g,0,i" description="info=*,a,C,g,0,i" format="Username: &quot;$10&quot;, Type: Ascii, Action: Compressed, Mode: Guest, Auth_Used: None, Status: Incomplete" matcherInput="$13,$6,$7,$9,$12,$14" version="1" version_type="int"></FastFormatter>
				<FastFormatter _type="null" condition="\*,a,C,g,1,c" description="info=*,a,C,g,1,c" format="Username: &quot;$10&quot;, Type: Ascii, Action: Compressed, Mode: Guest, Auth_Used: RFC931, Status: Complete" matcherInput="$13,$6,$7,$9,$12,$14" version="1" version_type="int"></FastFormatter>
				<FastFormatter _type="null" condition="\*,a,C,g,1,i" description="info=*,a,C,g,1,i" format="Username: &quot;$10&quot;, Type: Ascii, Action: Compressed, Mode: Guest, Auth_Used: RFC931, Status: Incomplete" matcherInput="$13,$6,$7,$9,$12,$14" version="1" version_type="int"></FastFormatter>
				<FastFormatter _type="null" condition="\*,a,C,r,0,c" description="info=*,a,C,r,0,c" format="Username: &quot;$10&quot;, Type: Ascii, Action: Compressed, Mode: Local, Auth_Used: None, Status: Complete" matcherInput="$13,$6,$7,$9,$12,$14" version="1" version_type="int"></FastFormatter>
				<FastFormatter _type="null" condition="\*,a,C,r,0,i" description="info=*,a,C,r,0,i" format="Username: &quot;$10&quot;, Type: Ascii, Action: Compressed, Mode: Local, Auth_Used: None, Status: Incomplete" matcherInput="$13,$6,$7,$9,$12,$14" version="1" version_type="int"></FastFormatter>
				<FastFormatter _type="null" condition="\*,a,C,r,1,c" description="info=*,a,C,r,1,c" format="Username: &quot;$10&quot;, Type: Ascii, Action: Compressed, Mode: Local, Auth_Used: RFC931, Status: Complete" matcherInput="$13,$6,$7,$9,$12,$14" version="1" version_type="int"></FastFormatter>
				<FastFormatter _type="null" condition="\*,a,C,r,1,i" description="info=*,a,C,r,1,i" format="Username: &quot;$10&quot;, Type: Ascii, Action: Compressed, Mode: Local, Auth_Used: RFC931, Status: Incomplete" matcherInput="$13,$6,$7,$9,$12,$14" version="1" version_type="int"></FastFormatter>
				<FastFormatter _type="null" condition="\*,a,_,a,0,c" description="info=*,a,_,a,0,c" format="Username: &quot;$10&quot;, Type: Ascii, Action: None, Mode: Anonymous, Auth_Used: None, Status: Complete" matcherInput="$13,$6,$7,$9,$12,$14" version="1" version_type="int"></FastFormatter>
				<FastFormatter _type="null" condition="\*,a,_,a,0,i" description="info=*,a,_,a,0,i" format="Username: &quot;$10&quot;, Type: Ascii, Action: None, Mode: Anonymous, Auth_Used: None, Status: Incomplete" matcherInput="$13,$6,$7,$9,$12,$14" version="1" version_type="int"></FastFormatter>
				<FastFormatter _type="null" condition="\*,a,_,a,1,c" description="info=*,a,_,a,1,c" format="Username: &quot;$10&quot;, Type: Ascii, Action: None, Mode: Anonymous, Auth_Used: RFC931, Status: Complete" matcherInput="$13,$6,$7,$9,$12,$14" version="1" version_type="int"></FastFormatter>
				<FastFormatter _type="null" condition="\*,a,_,a,1,i" description="info=*,a,_,a,1,i" format="Username: &quot;$10&quot;, Type: Ascii, Action: None, Mode: Anonymous, Auth_Used: RFC931, Status: Incomplete" matcherInput="$13,$6,$7,$9,$12,$14" version="1" version_type="int"></FastFormatter>
				<FastFormatter _type="null" condition="\*,a,_,g,0,c" description="info=*,a,_,g,0,c" format="Username: &quot;$10&quot;, Type: Ascii, Action: None, Mode: Guest, Auth_Used: None, Status: Complete" matcherInput="$13,$6,$7,$9,$12,$14" version="1" version_type="int"></FastFormatter>
				<FastFormatter _type="null" condition="\*,a,_,g,0,i" description="info=*,a,_,g,0,i" format="Username: &quot;$10&quot;, Type: Ascii, Action: None, Mode: Guest, Auth_Used: None, Status: Incomplete" matcherInput="$13,$6,$7,$9,$12,$14" version="1" version_type="int"></FastFormatter>
				<FastFormatter _type="null" condition="\*,a,_,g,1,c" description="info=*,a,_,g,1,c" format="Username: &quot;$10&quot;, Type: Ascii, Action: None, Mode: Guest, Auth_Used: RFC931, Status: Complete" matcherInput="$13,$6,$7,$9,$12,$14" version="1" version_type="int"></FastFormatter>
				<FastFormatter _type="null" condition="\*,a,_,g,1,i" description="info=*,a,_,g,1,i" format="Username: &quot;$10&quot;, Type: Ascii, Action: None, Mode: Guest, Auth_Used: RFC931, Status: Incomplete" matcherInput="$13,$6,$7,$9,$12,$14" version="1" version_type="int"></FastFormatter>
				<FastFormatter _type="null" condition="\*,a,_,r,0,c" description="info=*,a,_,r,0,c" format="Username: &quot;$10&quot;, Type: Ascii, Action: None, Mode: Local, Auth_Used: None, Status: Complete" matcherInput="$13,$6,$7,$9,$12,$14" version="1" version_type="int"></FastFormatter>
				<FastFormatter _type="null" condition="\*,a,_,r,0,i" description="info=*,a,_,r,0,i" format="Username: &quot;$10&quot;, Type: Ascii, Action: None, Mode: Local, Auth_Used: None, Status: Incomplete" matcherInput="$13,$6,$7,$9,$12,$14" version="1" version_type="int"></FastFormatter>
				<FastFormatter _type="null" condition="\*,a,_,r,1,c" description="info=*,a,_,r,1,c" format="Username: &quot;$10&quot;, Type: Ascii, Action: None, Mode: Local, Auth_Used: RFC931, Status: Complete" matcherInput="$13,$6,$7,$9,$12,$14" version="1" version_type="int"></FastFormatter>
				<FastFormatter _type="null" condition="\*,a,_,r,1,i" description="info=*,a,_,r,1,i" format="Username: &quot;$10&quot;, Type: Ascii, Action: None, Mode: Local, Auth_Used: RFC931, Status: Incomplete" matcherInput="$13,$6,$7,$9,$12,$14" version="1" version_type="int"></FastFormatter>
				<FastFormatter _type="null" condition="\*,a,U,a,0,c" description="info=*,a,U,a,0,c" format="Username: &quot;$10&quot;, Type: Ascii, Action: Not Compressed, Mode: Anonymous, Auth_Used: None, Status: Complete" matcherInput="$13,$6,$7,$9,$12,$14" version="1" version_type="int"></FastFormatter>
				<FastFormatter _type="null" condition="\*,a,U,a,0,i" description="info=*,a,U,a,0,i" format="Username: &quot;$10&quot;, Type: Ascii, Action: Not Compressed, Mode: Anonymous, Auth_Used: None, Status: Incomplete" matcherInput="$13,$6,$7,$9,$12,$14" version="1" version_type="int"></FastFormatter>
				<FastFormatter _type="null" condition="\*,a,U,a,1,c" description="info=*,a,U,a,1,c" format="Username: &quot;$10&quot;, Type: Ascii, Action: Not Compressed, Mode: Anonymous, Auth_Used: RFC931, Status: Complete" matcherInput="$13,$6,$7,$9,$12,$14" version="1" version_type="int"></FastFormatter>
				<FastFormatter _type="null" condition="\*,a,U,a,1,i" description="info=*,a,U,a,1,i" format="Username: &quot;$10&quot;, Type: Ascii, Action: Not Compressed, Mode: Anonymous, Auth_Used: RFC931, Status: Incomplete" matcherInput="$13,$6,$7,$9,$12,$14" version="1" version_type="int"></FastFormatter>
				<FastFormatter _type="null" condition="\*,a,U,g,0,c" description="info=*,a,U,g,0,c" format="Username: &quot;$10&quot;, Type: Ascii, Action: Not Compressed, Mode: Guest, Auth_Used: None, Status: Complete" matcherInput="$13,$6,$7,$9,$12,$14" version="1" version_type="int"></FastFormatter>
				<FastFormatter _type="null" condition="\*,a,U,g,0,i" description="info=*,a,U,g,0,i" format="Username: &quot;$10&quot;, Type: Ascii, Action: Not Compressed, Mode: Guest, Auth_Used: None, Status: Incomplete" matcherInput="$13,$6,$7,$9,$12,$14" version="1" version_type="int"></FastFormatter>
				<FastFormatter _type="null" condition="\*,a,U,g,1,c" description="info=*,a,U,g,1,c" format="Username: &quot;$10&quot;, Type: Ascii, Action: Not Compressed, Mode: Guest, Auth_Used: RFC931, Status: Complete" matcherInput="$13,$6,$7,$9,$12,$14" version="1" version_type="int"></FastFormatter>
				<FastFormatter _type="null" condition="\*,a,U,g,1,i" description="info=*,a,U,g,1,i" format="Username: &quot;$10&quot;, Type: Ascii, Action: Not Compressed, Mode: Guest, Auth_Used: RFC931, Status: Incomplete" matcherInput="$13,$6,$7,$9,$12,$14" version="1" version_type="int"></FastFormatter>
				<FastFormatter _type="null" condition="\*,a,U,r,0,c" description="info=*,a,U,r,0,c" format="Username: &quot;$10&quot;, Type: Ascii, Action: Not Compressed, Mode: Local, Auth_Used: None, Status: Complete" matcherInput="$13,$6,$7,$9,$12,$14" version="1" version_type="int"></FastFormatter>
				<FastFormatter _type="null" condition="\*,a,U,r,0,i" description="info=*,a,U,r,0,i" format="Username: &quot;$10&quot;, Type: Ascii, Action: Not Compressed, Mode: Local, Auth_Used: None, Status: Incomplete" matcherInput="$13,$6,$7,$9,$12,$14" version="1" version_type="int"></FastFormatter>
				<FastFormatter _type="null" condition="\*,a,U,r,1,c" description="info=*,a,U,r,1,c" format="Username: &quot;$10&quot;, Type: Ascii, Action: Not Compressed, Mode: Local, Auth_Used: RFC931, Status: Complete" matcherInput="$13,$6,$7,$9,$12,$14" version="1" version_type="int"></FastFormatter>
				<FastFormatter _type="null" condition="\*,a,U,r,1,i" description="info=*,a,U,r,1,i" format="Username: &quot;$10&quot;, Type: Ascii, Action: Not Compressed, Mode: Local, Auth_Used: RFC931, Status: Incomplete" matcherInput="$13,$6,$7,$9,$12,$14" version="1" version_type="int"></FastFormatter>
				<FastFormatter _type="null" condition="\*,b,T,a,0,c" description="info=*,b,T,a,0,c" format="Username: &quot;$10&quot;, Type: Binary, Action: Archived, Mode: Anonymous, Auth_Used: None, Status: Complete" matcherInput="$13,$6,$7,$9,$12,$14" version="1" version_type="int"></FastFormatter>
				<FastFormatter _type="null" condition="\*,b,T,a,0,i" description="info=*,b,T,a,0,i" format="Username: &quot;$10&quot;, Type: Binary, Action: Archived, Mode: Anonymous, Auth_Used: None, Status: Incomplete" matcherInput="$13,$6,$7,$9,$12,$14" version="1" version_type="int"></FastFormatter>
				<FastFormatter _type="null" condition="\*,b,T,a,1,c" description="info=*,b,T,a,1,c" format="Username: &quot;$10&quot;, Type: Binary, Action: Archived, Mode: Anonymous, Auth_Used: RFC931, Status: Complete" matcherInput="$13,$6,$7,$9,$12,$14" version="1" version_type="int"></FastFormatter>
				<FastFormatter _type="null" condition="\*,b,T,a,1,i" description="info=*,b,T,a,1,i" format="Username: &quot;$10&quot;, Type: Binary, Action: Archived, Mode: Anonymous, Auth_Used: RFC931, Status: Incomplete" matcherInput="$13,$6,$7,$9,$12,$14" version="1" version_type="int"></FastFormatter>
				<FastFormatter _type="null" condition="\*,b,T,g,0,c" description="info=*,b,T,g,0,c" format="Username: &quot;$10&quot;, Type: Binary, Action: Archived, Mode: Guest, Auth_Used: None, Status: Complete" matcherInput="$13,$6,$7,$9,$12,$14" version="1" version_type="int"></FastFormatter>
				<FastFormatter _type="null" condition="\*,b,T,g,0,i" description="info=*,b,T,g,0,i" format="Username: &quot;$10&quot;, Type: Binary, Action: Archived, Mode: Guest, Auth_Used: None, Status: Incomplete" matcherInput="$13,$6,$7,$9,$12,$14" version="1" version_type="int"></FastFormatter>
				<FastFormatter _type="null" condition="\*,b,T,g,1,c" description="info=*,b,T,g,1,c" format="Username: &quot;$10&quot;, Type: Binary, Action: Archived, Mode: Guest, Auth_Used: RFC931, Status: Complete" matcherInput="$13,$6,$7,$9,$12,$14" version="1" version_type="int"></FastFormatter>
				<FastFormatter _type="null" condition="\*,b,T,g,1,i" description="info=*,b,T,g,1,i" format="Username: &quot;$10&quot;, Type: Binary, Action: Archived, Mode: Guest, Auth_Used: RFC931, Status: Incomplete" matcherInput="$13,$6,$7,$9,$12,$14" version="1" version_type="int"></FastFormatter>
				<FastFormatter _type="null" condition="\*,b,T,r,0,c" description="info=*,b,T,r,0,c" format="Username: &quot;$10&quot;, Type: Binary, Action: Archived, Mode: Local, Auth_Used: None, Status: Complete" matcherInput="$13,$6,$7,$9,$12,$14" version="1" version_type="int"></FastFormatter>
				<FastFormatter _type="null" condition="\*,b,T,r,0,i" description="info=*,b,T,r,0,i" format="Username: &quot;$10&quot;, Type: Binary, Action: Archived, Mode: Local, Auth_Used: None, Status: Incomplete" matcherInput="$13,$6,$7,$9,$12,$14" version="1" version_type="int"></FastFormatter>
				<FastFormatter _type="null" condition="\*,b,T,r,1,c" description="info=*,b,T,r,1,c" format="Username: &quot;$10&quot;, Type: Binary, Action: Archived, Mode: Local, Auth_Used: RFC931, Status: Complete" matcherInput="$13,$6,$7,$9,$12,$14" version="1" version_type="int"></FastFormatter>
				<FastFormatter _type="null" condition="\*,b,T,r,1,i" description="info=*,b,T,r,1,i" format="Username: &quot;$10&quot;, Type: Binary, Action: Archived, Mode: Local, Auth_Used: RFC931, Status: Incomplete" matcherInput="$13,$6,$7,$9,$12,$14" version="1" version_type="int"></FastFormatter>
				<FastFormatter _type="null" condition="\*,b,C,a,0,c" description="info=*,b,C,a,0,c" format="Username: &quot;$10&quot;, Type: Binary, Action: Compressed, Mode: Anonymous, Auth_Used: None, Status: Complete" matcherInput="$13,$6,$7,$9,$12,$14" version="1" version_type="int"></FastFormatter>
				<FastFormatter _type="null" condition="\*,b,C,a,0,i" description="info=*,b,C,a,0,i" format="Username: &quot;$10&quot;, Type: Binary, Action: Compressed, Mode: Anonymous, Auth_Used: None, Status: Incomplete" matcherInput="$13,$6,$7,$9,$12,$14" version="1" version_type="int"></FastFormatter>
				<FastFormatter _type="null" condition="\*,b,C,a,1,c" description="info=*,b,C,a,1,c" format="Username: &quot;$10&quot;, Type: Binary, Action: Compressed, Mode: Anonymous, Auth_Used: RFC931, Status: Complete" matcherInput="$13,$6,$7,$9,$12,$14" version="1" version_type="int"></FastFormatter>
				<FastFormatter _type="null" condition="\*,b,C,a,1,i" description="info=*,b,C,a,1,i" format="Username: &quot;$10&quot;, Type: Binary, Action: Compressed, Mode: Anonymous, Auth_Used: RFC931, Status: Incomplete" matcherInput="$13,$6,$7,$9,$12,$14" version="1" version_type="int"></FastFormatter>
				<FastFormatter _type="null" condition="\*,b,C,g,0,c" description="info=*,b,C,g,0,c" format="Username: &quot;$10&quot;, Type: Binary, Action: Compressed, Mode: Guest, Auth_Used: None, Status: Complete" matcherInput="$13,$6,$7,$9,$12,$14" version="1" version_type="int"></FastFormatter>
				<FastFormatter _type="null" condition="\*,b,C,g,0,i" description="info=*,b,C,g,0,i" format="Username: &quot;$10&quot;, Type: Binary, Action: Compressed, Mode: Guest, Auth_Used: None, Status: Incomplete" matcherInput="$13,$6,$7,$9,$12,$14" version="1" version_type="int"></FastFormatter>
				<FastFormatter _type="null" condition="\*,b,C,g,1,c" description="info=*,b,C,g,1,c" format="Username: &quot;$10&quot;, Type: Binary, Action: Compressed, Mode: Guest, Auth_Used: RFC931, Status: Complete" matcherInput="$13,$6,$7,$9,$12,$14" version="1" version_type="int"></FastFormatter>
				<FastFormatter _type="null" condition="\*,b,C,g,1,i" description="info=*,b,C,g,1,i" format="Username: &quot;$10&quot;, Type: Binary, Action: Compressed, Mode: Guest, Auth_Used: RFC931, Status: Incomplete" matcherInput="$13,$6,$7,$9,$12,$14" version="1" version_type="int"></FastFormatter>
				<FastFormatter _type="null" condition="\*,b,C,r,0,c" description="info=*,b,C,r,0,c" format="Username: &quot;$10&quot;, Type: Binary, Action: Compressed, Mode: Local, Auth_Used: None, Status: Complete" matcherInput="$13,$6,$7,$9,$12,$14" version="1" version_type="int"></FastFormatter>
				<FastFormatter _type="null" condition="\*,b,C,r,0,i" description="info=*,b,C,r,0,i" format="Username: &quot;$10&quot;, Type: Binary, Action: Compressed, Mode: Local, Auth_Used: None, Status: Incomplete" matcherInput="$13,$6,$7,$9,$12,$14" version="1" version_type="int"></FastFormatter>
				<FastFormatter _type="null" condition="\*,b,C,r,1,c" description="info=*,b,C,r,1,c" format="Username: &quot;$10&quot;, Type: Binary, Action: Compressed, Mode: Local, Auth_Used: RFC931, Status: Complete" matcherInput="$13,$6,$7,$9,$12,$14" version="1" version_type="int"></FastFormatter>
				<FastFormatter _type="null" condition="\*,b,C,r,1,i" description="info=*,b,C,r,1,i" format="Username: &quot;$10&quot;, Type: Binary, Action: Compressed, Mode: Local, Auth_Used: RFC931, Status: Incomplete" matcherInput="$13,$6,$7,$9,$12,$14" version="1" version_type="int"></FastFormatter>
				<FastFormatter _type="null" condition="\*,b,_,a,0,c" description="info=*,b,_,a,0,c" format="Username: &quot;$10&quot;, Type: Binary, Action: None, Mode: Anonymous, Auth_Used: None, Status: Complete" matcherInput="$13,$6,$7,$9,$12,$14" version="1" version_type="int"></FastFormatter>
				<FastFormatter _type="null" condition="\*,b,_,a,0,i" description="info=*,b,_,a,0,i" format="Username: &quot;$10&quot;, Type: Binary, Action: None, Mode: Anonymous, Auth_Used: None, Status: Incomplete" matcherInput="$13,$6,$7,$9,$12,$14" version="1" version_type="int"></FastFormatter>
				<FastFormatter _type="null" condition="\*,b,_,a,1,c" description="info=*,b,_,a,1,c" format="Username: &quot;$10&quot;, Type: Binary, Action: None, Mode: Anonymous, Auth_Used: RFC931, Status: Complete" matcherInput="$13,$6,$7,$9,$12,$14" version="1" version_type="int"></FastFormatter>
				<FastFormatter _type="null" condition="\*,b,_,a,1,i" description="info=*,b,_,a,1,i" format="Username: &quot;$10&quot;, Type: Binary, Action: None, Mode: Anonymous, Auth_Used: RFC931, Status: Incomplete" matcherInput="$13,$6,$7,$9,$12,$14" version="1" version_type="int"></FastFormatter>
				<FastFormatter _type="null" condition="\*,b,_,g,0,c" description="info=*,b,_,g,0,c" format="Username: &quot;$10&quot;, Type: Binary, Action: None, Mode: Guest, Auth_Used: None, Status: Complete" matcherInput="$13,$6,$7,$9,$12,$14" version="1" version_type="int"></FastFormatter>
				<FastFormatter _type="null" condition="\*,b,_,g,0,i" description="info=*,b,_,g,0,i" format="Username: &quot;$10&quot;, Type: Binary, Action: None, Mode: Guest, Auth_Used: None, Status: Incomplete" matcherInput="$13,$6,$7,$9,$12,$14" version="1" version_type="int"></FastFormatter>
				<FastFormatter _type="null" condition="\*,b,_,g,1,c" description="info=*,b,_,g,1,c" format="Username: &quot;$10&quot;, Type: Binary, Action: None, Mode: Guest, Auth_Used: RFC931, Status: Complete" matcherInput="$13,$6,$7,$9,$12,$14" version="1" version_type="int"></FastFormatter>
				<FastFormatter _type="null" condition="\*,b,_,g,1,i" description="info=*,b,_,g,1,i" format="Username: &quot;$10&quot;, Type: Binary, Action: None, Mode: Guest, Auth_Used: RFC931, Status: Incomplete" matcherInput="$13,$6,$7,$9,$12,$14" version="1" version_type="int"></FastFormatter>
				<FastFormatter _type="null" condition="\*,b,_,r,0,c" description="info=*,b,_,r,0,c" format="Username: &quot;$10&quot;, Type: Binary, Action: None, Mode: Local, Auth_Used: None, Status: Complete" matcherInput="$13,$6,$7,$9,$12,$14" version="1" version_type="int"></FastFormatter>
				<FastFormatter _type="null" condition="\*,b,_,r,0,i" description="info=*,b,_,r,0,i" format="Username: &quot;$10&quot;, Type: Binary, Action: None, Mode: Local, Auth_Used: None, Status: Incomplete" matcherInput="$13,$6,$7,$9,$12,$14" version="1" version_type="int"></FastFormatter>
				<FastFormatter _type="null" condition="\*,b,_,r,1,c" description="info=*,b,_,r,1,c" format="Username: &quot;$10&quot;, Type: Binary, Action: None, Mode: Local, Auth_Used: RFC931, Status: Complete" matcherInput="$13,$6,$7,$9,$12,$14" version="1" version_type="int"></FastFormatter>
				<FastFormatter _type="null" condition="\*,b,_,r,1,i" description="info=*,b,_,r,1,i" format="Username: &quot;$10&quot;, Type: Binary, Action: None, Mode: Local, Auth_Used: RFC931, Status: Incomplete" matcherInput="$13,$6,$7,$9,$12,$14" version="1" version_type="int"></FastFormatter>
				<FastFormatter _type="null" condition="\*,b,U,a,0,c" description="info=*,b,U,a,0,c" format="Username: &quot;$10&quot;, Type: Binary, Action: Not Compressed, Mode: Anonymous, Auth_Used: None, Status: Complete" matcherInput="$13,$6,$7,$9,$12,$14" version="1" version_type="int"></FastFormatter>
				<FastFormatter _type="null" condition="\*,b,U,a,0,i" description="info=*,b,U,a,0,i" format="Username: &quot;$10&quot;, Type: Binary, Action: Not Compressed, Mode: Anonymous, Auth_Used: None, Status: Incomplete" matcherInput="$13,$6,$7,$9,$12,$14" version="1" version_type="int"></FastFormatter>
				<FastFormatter _type="null" condition="\*,b,U,a,1,c" description="info=*,b,U,a,1,c" format="Username: &quot;$10&quot;, Type: Binary, Action: Not Compressed, Mode: Anonymous, Auth_Used: RFC931, Status: Complete" matcherInput="$13,$6,$7,$9,$12,$14" version="1" version_type="int"></FastFormatter>
				<FastFormatter _type="null" condition="\*,b,U,a,1,i" description="info=*,b,U,a,1,i" format="Username: &quot;$10&quot;, Type: Binary, Action: Not Compressed, Mode: Anonymous, Auth_Used: RFC931, Status: Incomplete" matcherInput="$13,$6,$7,$9,$12,$14" version="1" version_type="int"></FastFormatter>
				<FastFormatter _type="null" condition="\*,b,U,g,0,c" description="info=*,b,U,g,0,c" format="Username: &quot;$10&quot;, Type: Binary, Action: Not Compressed, Mode: Guest, Auth_Used: None, Status: Complete" matcherInput="$13,$6,$7,$9,$12,$14" version="1" version_type="int"></FastFormatter>
				<FastFormatter _type="null" condition="\*,b,U,g,0,i" description="info=*,b,U,g,0,i" format="Username: &quot;$10&quot;, Type: Binary, Action: Not Compressed, Mode: Guest, Auth_Used: None, Status: Incomplete" matcherInput="$13,$6,$7,$9,$12,$14" version="1" version_type="int"></FastFormatter>
				<FastFormatter _type="null" condition="\*,b,U,g,1,c" description="info=*,b,U,g,1,c" format="Username: &quot;$10&quot;, Type: Binary, Action: Not Compressed, Mode: Guest, Auth_Used: RFC931, Status: Complete" matcherInput="$13,$6,$7,$9,$12,$14" version="1" version_type="int"></FastFormatter>
				<FastFormatter _type="null" condition="\*,b,U,g,1,i" description="info=*,b,U,g,1,i" format="Username: &quot;$10&quot;, Type: Binary, Action: Not Compressed, Mode: Guest, Auth_Used: RFC931, Status: Incomplete" matcherInput="$13,$6,$7,$9,$12,$14" version="1" version_type="int"></FastFormatter>
				<FastFormatter _type="null" condition="\*,b,U,r,0,c" description="info=*,b,U,r,0,c" format="Username: &quot;$10&quot;, Type: Binary, Action: Not Compressed, Mode: Local, Auth_Used: None, Status: Complete" matcherInput="$13,$6,$7,$9,$12,$14" version="1" version_type="int"></FastFormatter>
				<FastFormatter _type="null" condition="\*,b,U,r,0,i" description="info=*,b,U,r,0,i" format="Username: &quot;$10&quot;, Type: Binary, Action: Not Compressed, Mode: Local, Auth_Used: None, Status: Incomplete" matcherInput="$13,$6,$7,$9,$12,$14" version="1" version_type="int"></FastFormatter>
				<FastFormatter _type="null" condition="\*,b,U,r,1,c" description="info=*,b,U,r,1,c" format="Username: &quot;$10&quot;, Type: Binary, Action: Not Compressed, Mode: Local, Auth_Used: RFC931, Status: Complete" matcherInput="$13,$6,$7,$9,$12,$14" version="1" version_type="int"></FastFormatter>
				<FastFormatter _type="null" condition="\*,b,U,r,1,i" description="info=*,b,U,r,1,i" format="Username: &quot;$10&quot;, Type: Binary, Action: Not Compressed, Mode: Local, Auth_Used: RFC931, Status: Incomplete" matcherInput="$13,$6,$7,$9,$12,$14" version="1" version_type="int"></FastFormatter>
				<FastFormatter _type="null" condition="a,T,a,0,c" description="info=a,T,a,0,c" format="Username: &quot;$10&quot;, AuthID: &quot;$13&quot;, Type: Ascii, Action: Archived, Mode: Anonymous, Auth_Used: None, Status: Complete" matcherInput="$6,$7,$9,$12,$14" version="1" version_type="int"></FastFormatter>
				<FastFormatter _type="null" condition="a,T,a,0,i" description="info=a,T,a,0,i" format="Username: &quot;$10&quot;, AuthID: &quot;$13&quot;, Type: Ascii, Action: Archived, Mode: Anonymous, Auth_Used: None, Status: Incomplete" matcherInput="$6,$7,$9,$12,$14" version="1" version_type="int"></FastFormatter>
				<FastFormatter _type="null" condition="a,T,a,1,c" description="info=a,T,a,1,c" format="Username: &quot;$10&quot;, AuthID: &quot;$13&quot;, Type: Ascii, Action: Archived, Mode: Anonymous, Auth_Used: RFC931, Status: Complete" matcherInput="$6,$7,$9,$12,$14" version="1" version_type="int"></FastFormatter>
				<FastFormatter _type="null" condition="a,T,a,1,i" description="info=a,T,a,1,i" format="Username: &quot;$10&quot;, AuthID: &quot;$13&quot;, Type: Ascii, Action: Archived, Mode: Anonymous, Auth_Used: RFC931, Status: Incomplete" matcherInput="$6,$7,$9,$12,$14" version="1" version_type="int"></FastFormatter>
				<FastFormatter _type="null" condition="a,T,g,0,c" description="info=a,T,g,0,c" format="Username: &quot;$10&quot;, AuthID: &quot;$13&quot;, Type: Ascii, Action: Archived, Mode: Guest, Auth_Used: None, Status: Complete" matcherInput="$6,$7,$9,$12,$14" version="1" version_type="int"></FastFormatter>
				<FastFormatter _type="null" condition="a,T,g,0,i" description="info=a,T,g,0,i" format="Username: &quot;$10&quot;, AuthID: &quot;$13&quot;, Type: Ascii, Action: Archived, Mode: Guest, Auth_Used: None, Status: Incomplete" matcherInput="$6,$7,$9,$12,$14" version="1" version_type="int"></FastFormatter>
				<FastFormatter _type="null" condition="a,T,g,1,c" description="info=a,T,g,1,c" format="Username: &quot;$10&quot;, AuthID: &quot;$13&quot;, Type: Ascii, Action: Archived, Mode: Guest, Auth_Used: RFC931, Status: Complete" matcherInput="$6,$7,$9,$12,$14" version="1" version_type="int"></FastFormatter>
				<FastFormatter _type="null" condition="a,T,g,1,i" description="info=a,T,g,1,i" format="Username: &quot;$10&quot;, AuthID: &quot;$13&quot;, Type: Ascii, Action: Archived, Mode: Guest, Auth_Used: RFC931, Status: Incomplete" matcherInput="$6,$7,$9,$12,$14" version="1" version_type="int"></FastFormatter>
				<FastFormatter _type="null" condition="a,T,r,0,c" description="info=a,T,r,0,c" format="Username: &quot;$10&quot;, AuthID: &quot;$13&quot;, Type: Ascii, Action: Archived, Mode: Local, Auth_Used: None, Status: Complete" matcherInput="$6,$7,$9,$12,$14" version="1" version_type="int"></FastFormatter>
				<FastFormatter _type="null" condition="a,T,r,0,i" description="info=a,T,r,0,i" format="Username: &quot;$10&quot;, AuthID: &quot;$13&quot;, Type: Ascii, Action: Archived, Mode: Local, Auth_Used: None, Status: Incomplete" matcherInput="$6,$7,$9,$12,$14" version="1" version_type="int"></FastFormatter>
				<FastFormatter _type="null" condition="a,T,r,1,c" description="info=a,T,r,1,c" format="Username: &quot;$10&quot;, AuthID: &quot;$13&quot;, Type: Ascii, Action: Archived, Mode: Local, Auth_Used: RFC931, Status: Complete" matcherInput="$6,$7,$9,$12,$14" version="1" version_type="int"></FastFormatter>
				<FastFormatter _type="null" condition="a,T,r,1,i" description="info=a,T,r,1,i" format="Username: &quot;$10&quot;, AuthID: &quot;$13&quot;, Type: Ascii, Action: Archived, Mode: Local, Auth_Used: RFC931, Status: Incomplete" matcherInput="$6,$7,$9,$12,$14" version="1" version_type="int"></FastFormatter>
				<FastFormatter _type="null" condition="a,C,a,0,c" description="info=a,C,a,0,c" format="Username: &quot;$10&quot;, AuthID: &quot;$13&quot;, Type: Ascii, Action: Compressed, Mode: Anonymous, Auth_Used: None, Status: Complete" matcherInput="$6,$7,$9,$12,$14" version="1" version_type="int"></FastFormatter>
				<FastFormatter _type="null" condition="a,C,a,0,i" description="info=a,C,a,0,i" format="Username: &quot;$10&quot;, AuthID: &quot;$13&quot;, Type: Ascii, Action: Compressed, Mode: Anonymous, Auth_Used: None, Status: Incomplete" matcherInput="$6,$7,$9,$12,$14" version="1" version_type="int"></FastFormatter>
				<FastFormatter _type="null" condition="a,C,a,1,c" description="info=a,C,a,1,c" format="Username: &quot;$10&quot;, AuthID: &quot;$13&quot;, Type: Ascii, Action: Compressed, Mode: Anonymous, Auth_Used: RFC931, Status: Complete" matcherInput="$6,$7,$9,$12,$14" version="1" version_type="int"></FastFormatter>
				<FastFormatter _type="null" condition="a,C,a,1,i" description="info=a,C,a,1,i" format="Username: &quot;$10&quot;, AuthID: &quot;$13&quot;, Type: Ascii, Action: Compressed, Mode: Anonymous, Auth_Used: RFC931, Status: Incomplete" matcherInput="$6,$7,$9,$12,$14" version="1" version_type="int"></FastFormatter>
				<FastFormatter _type="null" condition="a,C,g,0,c" description="info=a,C,g,0,c" format="Username: &quot;$10&quot;, AuthID: &quot;$13&quot;, Type: Ascii, Action: Compressed, Mode: Guest, Auth_Used: None, Status: Complete" matcherInput="$6,$7,$9,$12,$14" version="1" version_type="int"></FastFormatter>
				<FastFormatter _type="null" condition="a,C,g,0,i" description="info=a,C,g,0,i" format="Username: &quot;$10&quot;, AuthID: &quot;$13&quot;, Type: Ascii, Action: Compressed, Mode: Guest, Auth_Used: None, Status: Incomplete" matcherInput="$6,$7,$9,$12,$14" version="1" version_type="int"></FastFormatter>
				<FastFormatter _type="null" condition="a,C,g,1,c" description="info=a,C,g,1,c" format="Username: &quot;$10&quot;, AuthID: &quot;$13&quot;, Type: Ascii, Action: Compressed, Mode: Guest, Auth_Used: RFC931, Status: Complete" matcherInput="$6,$7,$9,$12,$14" version="1" version_type="int"></FastFormatter>
				<FastFormatter _type="null" condition="a,C,g,1,i" description="info=a,C,g,1,i" format="Username: &quot;$10&quot;, AuthID: &quot;$13&quot;, Type: Ascii, Action: Compressed, Mode: Guest, Auth_Used: RFC931, Status: Incomplete" matcherInput="$6,$7,$9,$12,$14" version="1" version_type="int"></FastFormatter>
				<FastFormatter _type="null" condition="a,C,r,0,c" description="info=a,C,r,0,c" format="Username: &quot;$10&quot;, AuthID: &quot;$13&quot;, Type: Ascii, Action: Compressed, Mode: Local, Auth_Used: None, Status: Complete" matcherInput="$6,$7,$9,$12,$14" version="1" version_type="int"></FastFormatter>
				<FastFormatter _type="null" condition="a,C,r,0,i" description="info=a,C,r,0,i" format="Username: &quot;$10&quot;, AuthID: &quot;$13&quot;, Type: Ascii, Action: Compressed, Mode: Local, Auth_Used: None, Status: Incomplete" matcherInput="$6,$7,$9,$12,$14" version="1" version_type="int"></FastFormatter>
				<FastFormatter _type="null" condition="a,C,r,1,c" description="info=a,C,r,1,c" format="Username: &quot;$10&quot;, AuthID: &quot;$13&quot;, Type: Ascii, Action: Compressed, Mode: Local, Auth_Used: RFC931, Status: Complete" matcherInput="$6,$7,$9,$12,$14" version="1" version_type="int"></FastFormatter>
				<FastFormatter _type="null" condition="a,C,r,1,i" description="info=a,C,r,1,i" format="Username: &quot;$10&quot;, AuthID: &quot;$13&quot;, Type: Ascii, Action: Compressed, Mode: Local, Auth_Used: RFC931, Status: Incomplete" matcherInput="$6,$7,$9,$12,$14" version="1" version_type="int"></FastFormatter>
				<FastFormatter _type="null" condition="a,_,a,0,c" description="info=a,_,a,0,c" format="Username: &quot;$10&quot;, AuthID: &quot;$13&quot;, Type: Ascii, Action: None, Mode: Anonymous, Auth_Used: None, Status: Complete" matcherInput="$6,$7,$9,$12,$14" version="1" version_type="int"></FastFormatter>
				<FastFormatter _type="null" condition="a,_,a,0,i" description="info=a,_,a,0,i" format="Username: &quot;$10&quot;, AuthID: &quot;$13&quot;, Type: Ascii, Action: None, Mode: Anonymous, Auth_Used: None, Status: Incomplete" matcherInput="$6,$7,$9,$12,$14" version="1" version_type="int"></FastFormatter>
				<FastFormatter _type="null" condition="a,_,a,1,c" description="info=a,_,a,1,c" format="Username: &quot;$10&quot;, AuthID: &quot;$13&quot;, Type: Ascii, Action: None, Mode: Anonymous, Auth_Used: RFC931, Status: Complete" matcherInput="$6,$7,$9,$12,$14" version="1" version_type="int"></FastFormatter>
				<FastFormatter _type="null" condition="a,_,a,1,i" description="info=a,_,a,1,i" format="Username: &quot;$10&quot;, AuthID: &quot;$13&quot;, Type: Ascii, Action: None, Mode: Anonymous, Auth_Used: RFC931, Status: Incomplete" matcherInput="$6,$7,$9,$12,$14" version="1" version_type="int"></FastFormatter>
				<FastFormatter _type="null" condition="a,_,g,0,c" description="info=a,_,g,0,c" format="Username: &quot;$10&quot;, AuthID: &quot;$13&quot;, Type: Ascii, Action: None, Mode: Guest, Auth_Used: None, Status: Complete" matcherInput="$6,$7,$9,$12,$14" version="1" version_type="int"></FastFormatter>
				<FastFormatter _type="null" condition="a,_,g,0,i" description="info=a,_,g,0,i" format="Username: &quot;$10&quot;, AuthID: &quot;$13&quot;, Type: Ascii, Action: None, Mode: Guest, Auth_Used: None, Status: Incomplete" matcherInput="$6,$7,$9,$12,$14" version="1" version_type="int"></FastFormatter>
				<FastFormatter _type="null" condition="a,_,g,1,c" description="info=a,_,g,1,c" format="Username: &quot;$10&quot;, AuthID: &quot;$13&quot;, Type: Ascii, Action: None, Mode: Guest, Auth_Used: RFC931, Status: Complete" matcherInput="$6,$7,$9,$12,$14" version="1" version_type="int"></FastFormatter>
				<FastFormatter _type="null" condition="a,_,g,1,i" description="info=a,_,g,1,i" format="Username: &quot;$10&quot;, AuthID: &quot;$13&quot;, Type: Ascii, Action: None, Mode: Guest, Auth_Used: RFC931, Status: Incomplete" matcherInput="$6,$7,$9,$12,$14" version="1" version_type="int"></FastFormatter>
				<FastFormatter _type="null" condition="a,_,r,0,c" description="info=a,_,r,0,c" format="Username: &quot;$10&quot;, AuthID: &quot;$13&quot;, Type: Ascii, Action: None, Mode: Local, Auth_Used: None, Status: Complete" matcherInput="$6,$7,$9,$12,$14" version="1" version_type="int"></FastFormatter>
				<FastFormatter _type="null" condition="a,_,r,0,i" description="info=a,_,r,0,i" format="Username: &quot;$10&quot;, AuthID: &quot;$13&quot;, Type: Ascii, Action: None, Mode: Local, Auth_Used: None, Status: Incomplete" matcherInput="$6,$7,$9,$12,$14" version="1" version_type="int"></FastFormatter>
				<FastFormatter _type="null" condition="a,_,r,1,c" description="info=a,_,r,1,c" format="Username: &quot;$10&quot;, AuthID: &quot;$13&quot;, Type: Ascii, Action: None, Mode: Local, Auth_Used: RFC931, Status: Complete" matcherInput="$6,$7,$9,$12,$14" version="1" version_type="int"></FastFormatter>
				<FastFormatter _type="null" condition="a,_,r,1,i" description="info=a,_,r,1,i" format="Username: &quot;$10&quot;, AuthID: &quot;$13&quot;, Type: Ascii, Action: None, Mode: Local, Auth_Used: RFC931, Status: Incomplete" matcherInput="$6,$7,$9,$12,$14" version="1" version_type="int"></FastFormatter>
				<FastFormatter _type="null" condition="a,U,a,0,c" description="info=a,U,a,0,c" format="Username: &quot;$10&quot;, AuthID: &quot;$13&quot;, Type: Ascii, Action: Not Compressed, Mode: Anonymous, Auth_Used: None, Status: Complete" matcherInput="$6,$7,$9,$12,$14" version="1" version_type="int"></FastFormatter>
				<FastFormatter _type="null" condition="a,U,a,0,i" description="info=a,U,a,0,i" format="Username: &quot;$10&quot;, AuthID: &quot;$13&quot;, Type: Ascii, Action: Not Compressed, Mode: Anonymous, Auth_Used: None, Status: Incomplete" matcherInput="$6,$7,$9,$12,$14" version="1" version_type="int"></FastFormatter>
				<FastFormatter _type="null" condition="a,U,a,1,c" description="info=a,U,a,1,c" format="Username: &quot;$10&quot;, AuthID: &quot;$13&quot;, Type: Ascii, Action: Not Compressed, Mode: Anonymous, Auth_Used: RFC931, Status: Complete" matcherInput="$6,$7,$9,$12,$14" version="1" version_type="int"></FastFormatter>
				<FastFormatter _type="null" condition="a,U,a,1,i" description="info=a,U,a,1,i" format="Username: &quot;$10&quot;, AuthID: &quot;$13&quot;, Type: Ascii, Action: Not Compressed, Mode: Anonymous, Auth_Used: RFC931, Status: Incomplete" matcherInput="$6,$7,$9,$12,$14" version="1" version_type="int"></FastFormatter>
				<FastFormatter _type="null" condition="a,U,g,0,c" description="info=a,U,g,0,c" format="Username: &quot;$10&quot;, AuthID: &quot;$13&quot;, Type: Ascii, Action: Not Compressed, Mode: Guest, Auth_Used: None, Status: Complete" matcherInput="$6,$7,$9,$12,$14" version="1" version_type="int"></FastFormatter>
				<FastFormatter _type="null" condition="a,U,g,0,i" description="info=a,U,g,0,i" format="Username: &quot;$10&quot;, AuthID: &quot;$13&quot;, Type: Ascii, Action: Not Compressed, Mode: Guest, Auth_Used: None, Status: Incomplete" matcherInput="$6,$7,$9,$12,$14" version="1" version_type="int"></FastFormatter>
				<FastFormatter _type="null" condition="a,U,g,1,c" description="info=a,U,g,1,c" format="Username: &quot;$10&quot;, AuthID: &quot;$13&quot;, Type: Ascii, Action: Not Compressed, Mode: Guest, Auth_Used: RFC931, Status: Complete" matcherInput="$6,$7,$9,$12,$14" version="1" version_type="int"></FastFormatter>
				<FastFormatter _type="null" condition="a,U,g,1,i" description="info=a,U,g,1,i" format="Username: &quot;$10&quot;, AuthID: &quot;$13&quot;, Type: Ascii, Action: Not Compressed, Mode: Guest, Auth_Used: RFC931, Status: Incomplete" matcherInput="$6,$7,$9,$12,$14" version="1" version_type="int"></FastFormatter>
				<FastFormatter _type="null" condition="a,U,r,0,c" description="info=a,U,r,0,c" format="Username: &quot;$10&quot;, AuthID: &quot;$13&quot;, Type: Ascii, Action: Not Compressed, Mode: Local, Auth_Used: None, Status: Complete" matcherInput="$6,$7,$9,$12,$14" version="1" version_type="int"></FastFormatter>
				<FastFormatter _type="null" condition="a,U,r,0,i" description="info=a,U,r,0,i" format="Username: &quot;$10&quot;, AuthID: &quot;$13&quot;, Type: Ascii, Action: Not Compressed, Mode: Local, Auth_Used: None, Status: Incomplete" matcherInput="$6,$7,$9,$12,$14" version="1" version_type="int"></FastFormatter>
				<FastFormatter _type="null" condition="a,U,r,1,c" description="info=a,U,r,1,c" format="Username: &quot;$10&quot;, AuthID: &quot;$13&quot;, Type: Ascii, Action: Not Compressed, Mode: Local, Auth_Used: RFC931, Status: Complete" matcherInput="$6,$7,$9,$12,$14" version="1" version_type="int"></FastFormatter>
				<FastFormatter _type="null" condition="a,U,r,1,i" description="info=a,U,r,1,i" format="Username: &quot;$10&quot;, AuthID: &quot;$13&quot;, Type: Ascii, Action: Not Compressed, Mode: Local, Auth_Used: RFC931, Status: Incomplete" matcherInput="$6,$7,$9,$12,$14" version="1" version_type="int"></FastFormatter>
				<FastFormatter _type="null" condition="b,T,a,0,c" description="info=b,T,a,0,c" format="Username: &quot;$10&quot;, AuthID: &quot;$13&quot;, Type: Binary, Action: Archived, Mode: Anonymous, Auth_Used: None, Status: Complete" matcherInput="$6,$7,$9,$12,$14" version="1" version_type="int"></FastFormatter>
				<FastFormatter _type="null" condition="b,T,a,0,i" description="info=b,T,a,0,i" format="Username: &quot;$10&quot;, AuthID: &quot;$13&quot;, Type: Binary, Action: Archived, Mode: Anonymous, Auth_Used: None, Status: Incomplete" matcherInput="$6,$7,$9,$12,$14" version="1" version_type="int"></FastFormatter>
				<FastFormatter _type="null" condition="b,T,a,1,c" description="info=b,T,a,1,c" format="Username: &quot;$10&quot;, AuthID: &quot;$13&quot;, Type: Binary, Action: Archived, Mode: Anonymous, Auth_Used: RFC931, Status: Complete" matcherInput="$6,$7,$9,$12,$14" version="1" version_type="int"></FastFormatter>
				<FastFormatter _type="null" condition="b,T,a,1,i" description="info=b,T,a,1,i" format="Username: &quot;$10&quot;, AuthID: &quot;$13&quot;, Type: Binary, Action: Archived, Mode: Anonymous, Auth_Used: RFC931, Status: Incomplete" matcherInput="$6,$7,$9,$12,$14" version="1" version_type="int"></FastFormatter>
				<FastFormatter _type="null" condition="b,T,g,0,c" description="info=b,T,g,0,c" format="Username: &quot;$10&quot;, AuthID: &quot;$13&quot;, Type: Binary, Action: Archived, Mode: Guest, Auth_Used: None, Status: Complete" matcherInput="$6,$7,$9,$12,$14" version="1" version_type="int"></FastFormatter>
				<FastFormatter _type="null" condition="b,T,g,0,i" description="info=b,T,g,0,i" format="Username: &quot;$10&quot;, AuthID: &quot;$13&quot;, Type: Binary, Action: Archived, Mode: Guest, Auth_Used: None, Status: Incomplete" matcherInput="$6,$7,$9,$12,$14" version="1" version_type="int"></FastFormatter>
				<FastFormatter _type="null" condition="b,T,g,1,c" description="info=b,T,g,1,c" format="Username: &quot;$10&quot;, AuthID: &quot;$13&quot;, Type: Binary, Action: Archived, Mode: Guest, Auth_Used: RFC931, Status: Complete" matcherInput="$6,$7,$9,$12,$14" version="1" version_type="int"></FastFormatter>
				<FastFormatter _type="null" condition="b,T,g,1,i" description="info=b,T,g,1,i" format="Username: &quot;$10&quot;, AuthID: &quot;$13&quot;, Type: Binary, Action: Archived, Mode: Guest, Auth_Used: RFC931, Status: Incomplete" matcherInput="$6,$7,$9,$12,$14" version="1" version_type="int"></FastFormatter>
				<FastFormatter _type="null" condition="b,T,r,0,c" description="info=b,T,r,0,c" format="Username: &quot;$10&quot;, AuthID: &quot;$13&quot;, Type: Binary, Action: Archived, Mode: Local, Auth_Used: None, Status: Complete" matcherInput="$6,$7,$9,$12,$14" version="1" version_type="int"></FastFormatter>
				<FastFormatter _type="null" condition="b,T,r,0,i" description="info=b,T,r,0,i" format="Username: &quot;$10&quot;, AuthID: &quot;$13&quot;, Type: Binary, Action: Archived, Mode: Local, Auth_Used: None, Status: Incomplete" matcherInput="$6,$7,$9,$12,$14" version="1" version_type="int"></FastFormatter>
				<FastFormatter _type="null" condition="b,T,r,1,c" description="info=b,T,r,1,c" format="Username: &quot;$10&quot;, AuthID: &quot;$13&quot;, Type: Binary, Action: Archived, Mode: Local, Auth_Used: RFC931, Status: Complete" matcherInput="$6,$7,$9,$12,$14" version="1" version_type="int"></FastFormatter>
				<FastFormatter _type="null" condition="b,T,r,1,i" description="info=b,T,r,1,i" format="Username: &quot;$10&quot;, AuthID: &quot;$13&quot;, Type: Binary, Action: Archived, Mode: Local, Auth_Used: RFC931, Status: Incomplete" matcherInput="$6,$7,$9,$12,$14" version="1" version_type="int"></FastFormatter>
				<FastFormatter _type="null" condition="b,C,a,0,c" description="info=b,C,a,0,c" format="Username: &quot;$10&quot;, AuthID: &quot;$13&quot;, Type: Binary, Action: Compressed, Mode: Anonymous, Auth_Used: None, Status: Complete" matcherInput="$6,$7,$9,$12,$14" version="1" version_type="int"></FastFormatter>
				<FastFormatter _type="null" condition="b,C,a,0,i" description="info=b,C,a,0,i" format="Username: &quot;$10&quot;, AuthID: &quot;$13&quot;, Type: Binary, Action: Compressed, Mode: Anonymous, Auth_Used: None, Status: Incomplete" matcherInput="$6,$7,$9,$12,$14" version="1" version_type="int"></FastFormatter>
				<FastFormatter _type="null" condition="b,C,a,1,c" description="info=b,C,a,1,c" format="Username: &quot;$10&quot;, AuthID: &quot;$13&quot;, Type: Binary, Action: Compressed, Mode: Anonymous, Auth_Used: RFC931, Status: Complete" matcherInput="$6,$7,$9,$12,$14" version="1" version_type="int"></FastFormatter>
				<FastFormatter _type="null" condition="b,C,a,1,i" description="info=b,C,a,1,i" format="Username: &quot;$10&quot;, AuthID: &quot;$13&quot;, Type: Binary, Action: Compressed, Mode: Anonymous, Auth_Used: RFC931, Status: Incomplete" matcherInput="$6,$7,$9,$12,$14" version="1" version_type="int"></FastFormatter>
				<FastFormatter _type="null" condition="b,C,g,0,c" description="info=b,C,g,0,c" format="Username: &quot;$10&quot;, AuthID: &quot;$13&quot;, Type: Binary, Action: Compressed, Mode: Guest, Auth_Used: None, Status: Complete" matcherInput="$6,$7,$9,$12,$14" version="1" version_type="int"></FastFormatter>
				<FastFormatter _type="null" condition="b,C,g,0,i" description="info=b,C,g,0,i" format="Username: &quot;$10&quot;, AuthID: &quot;$13&quot;, Type: Binary, Action: Compressed, Mode: Guest, Auth_Used: None, Status: Incomplete" matcherInput="$6,$7,$9,$12,$14" version="1" version_type="int"></FastFormatter>
				<FastFormatter _type="null" condition="b,C,g,1,c" description="info=b,C,g,1,c" format="Username: &quot;$10&quot;, AuthID: &quot;$13&quot;, Type: Binary, Action: Compressed, Mode: Guest, Auth_Used: RFC931, Status: Complete" matcherInput="$6,$7,$9,$12,$14" version="1" version_type="int"></FastFormatter>
				<FastFormatter _type="null" condition="b,C,g,1,i" description="info=b,C,g,1,i" format="Username: &quot;$10&quot;, AuthID: &quot;$13&quot;, Type: Binary, Action: Compressed, Mode: Guest, Auth_Used: RFC931, Status: Incomplete" matcherInput="$6,$7,$9,$12,$14" version="1" version_type="int"></FastFormatter>
				<FastFormatter _type="null" condition="b,C,r,0,c" description="info=b,C,r,0,c" format="Username: &quot;$10&quot;, AuthID: &quot;$13&quot;, Type: Binary, Action: Compressed, Mode: Local, Auth_Used: None, Status: Complete" matcherInput="$6,$7,$9,$12,$14" version="1" version_type="int"></FastFormatter>
				<FastFormatter _type="null" condition="b,C,r,0,i" description="info=b,C,r,0,i" format="Username: &quot;$10&quot;, AuthID: &quot;$13&quot;, Type: Binary, Action: Compressed, Mode: Local, Auth_Used: None, Status: Incomplete" matcherInput="$6,$7,$9,$12,$14" version="1" version_type="int"></FastFormatter>
				<FastFormatter _type="null" condition="b,C,r,1,c" description="info=b,C,r,1,c" format="Username: &quot;$10&quot;, AuthID: &quot;$13&quot;, Type: Binary, Action: Compressed, Mode: Local, Auth_Used: RFC931, Status: Complete" matcherInput="$6,$7,$9,$12,$14" version="1" version_type="int"></FastFormatter>
				<FastFormatter _type="null" condition="b,C,r,1,i" description="info=b,C,r,1,i" format="Username: &quot;$10&quot;, AuthID: &quot;$13&quot;, Type: Binary, Action: Compressed, Mode: Local, Auth_Used: RFC931, Status: Incomplete" matcherInput="$6,$7,$9,$12,$14" version="1" version_type="int"></FastFormatter>
				<FastFormatter _type="null" condition="b,_,a,0,c" description="info=b,_,a,0,c" format="Username: &quot;$10&quot;, AuthID: &quot;$13&quot;, Type: Binary, Action: None, Mode: Anonymous, Auth_Used: None, Status: Complete" matcherInput="$6,$7,$9,$12,$14" version="1" version_type="int"></FastFormatter>
				<FastFormatter _type="null" condition="b,_,a,0,i" description="info=b,_,a,0,i" format="Username: &quot;$10&quot;, AuthID: &quot;$13&quot;, Type: Binary, Action: None, Mode: Anonymous, Auth_Used: None, Status: Incomplete" matcherInput="$6,$7,$9,$12,$14" version="1" version_type="int"></FastFormatter>
				<FastFormatter _type="null" condition="b,_,a,1,c" description="info=b,_,a,1,c" format="Username: &quot;$10&quot;, AuthID: &quot;$13&quot;, Type: Binary, Action: None, Mode: Anonymous, Auth_Used: RFC931, Status: Complete" matcherInput="$6,$7,$9,$12,$14" version="1" version_type="int"></FastFormatter>
				<FastFormatter _type="null" condition="b,_,a,1,i" description="info=b,_,a,1,i" format="Username: &quot;$10&quot;, AuthID: &quot;$13&quot;, Type: Binary, Action: None, Mode: Anonymous, Auth_Used: RFC931, Status: Incomplete" matcherInput="$6,$7,$9,$12,$14" version="1" version_type="int"></FastFormatter>
				<FastFormatter _type="null" condition="b,_,g,0,c" description="info=b,_,g,0,c" format="Username: &quot;$10&quot;, AuthID: &quot;$13&quot;, Type: Binary, Action: None, Mode: Guest, Auth_Used: None, Status: Complete" matcherInput="$6,$7,$9,$12,$14" version="1" version_type="int"></FastFormatter>
				<FastFormatter _type="null" condition="b,_,g,0,i" description="info=b,_,g,0,i" format="Username: &quot;$10&quot;, AuthID: &quot;$13&quot;, Type: Binary, Action: None, Mode: Guest, Auth_Used: None, Status: Incomplete" matcherInput="$6,$7,$9,$12,$14" version="1" version_type="int"></FastFormatter>
				<FastFormatter _type="null" condition="b,_,g,1,c" description="info=b,_,g,1,c" format="Username: &quot;$10&quot;, AuthID: &quot;$13&quot;, Type: Binary, Action: None, Mode: Guest, Auth_Used: RFC931, Status: Complete" matcherInput="$6,$7,$9,$12,$14" version="1" version_type="int"></FastFormatter>
				<FastFormatter _type="null" condition="b,_,g,1,i" description="info=b,_,g,1,i" format="Username: &quot;$10&quot;, AuthID: &quot;$13&quot;, Type: Binary, Action: None, Mode: Guest, Auth_Used: RFC931, Status: Incomplete" matcherInput="$6,$7,$9,$12,$14" version="1" version_type="int"></FastFormatter>
				<FastFormatter _type="null" condition="b,_,r,0,c" description="info=b,_,r,0,c" format="Username: &quot;$10&quot;, AuthID: &quot;$13&quot;, Type: Binary, Action: None, Mode: Local, Auth_Used: None, Status: Complete" matcherInput="$6,$7,$9,$12,$14" version="1" version_type="int"></FastFormatter>
				<FastFormatter _type="null" condition="b,_,r,0,i" description="info=b,_,r,0,i" format="Username: &quot;$10&quot;, AuthID: &quot;$13&quot;, Type: Binary, Action: None, Mode: Local, Auth_Used: None, Status: Incomplete" matcherInput="$6,$7,$9,$12,$14" version="1" version_type="int"></FastFormatter>
				<FastFormatter _type="null" condition="b,_,r,1,c" description="info=b,_,r,1,c" format="Username: &quot;$10&quot;, AuthID: &quot;$13&quot;, Type: Binary, Action: None, Mode: Local, Auth_Used: RFC931, Status: Complete" matcherInput="$6,$7,$9,$12,$14" version="1" version_type="int"></FastFormatter>
				<FastFormatter _type="null" condition="b,_,r,1,i" description="info=b,_,r,1,i" format="Username: &quot;$10&quot;, AuthID: &quot;$13&quot;, Type: Binary, Action: None, Mode: Local, Auth_Used: RFC931, Status: Incomplete" matcherInput="$6,$7,$9,$12,$14" version="1" version_type="int"></FastFormatter>
				<FastFormatter _type="null" condition="b,U,a,0,c" description="info=b,U,a,0,c" format="Username: &quot;$10&quot;, AuthID: &quot;$13&quot;, Type: Binary, Action: Not Compressed, Mode: Anonymous, Auth_Used: None, Status: Complete" matcherInput="$6,$7,$9,$12,$14" version="1" version_type="int"></FastFormatter>
				<FastFormatter _type="null" condition="b,U,a,0,i" description="info=b,U,a,0,i" format="Username: &quot;$10&quot;, AuthID: &quot;$13&quot;, Type: Binary, Action: Not Compressed, Mode: Anonymous, Auth_Used: None, Status: Incomplete" matcherInput="$6,$7,$9,$12,$14" version="1" version_type="int"></FastFormatter>
				<FastFormatter _type="null" condition="b,U,a,1,c" description="info=b,U,a,1,c" format="Username: &quot;$10&quot;, AuthID: &quot;$13&quot;, Type: Binary, Action: Not Compressed, Mode: Anonymous, Auth_Used: RFC931, Status: Complete" matcherInput="$6,$7,$9,$12,$14" version="1" version_type="int"></FastFormatter>
				<FastFormatter _type="null" condition="b,U,a,1,i" description="info=b,U,a,1,i" format="Username: &quot;$10&quot;, AuthID: &quot;$13&quot;, Type: Binary, Action: Not Compressed, Mode: Anonymous, Auth_Used: RFC931, Status: Incomplete" matcherInput="$6,$7,$9,$12,$14" version="1" version_type="int"></FastFormatter>
				<FastFormatter _type="null" condition="b,U,g,0,c" description="info=b,U,g,0,c" format="Username: &quot;$10&quot;, AuthID: &quot;$13&quot;, Type: Binary, Action: Not Compressed, Mode: Guest, Auth_Used: None, Status: Complete" matcherInput="$6,$7,$9,$12,$14" version="1" version_type="int"></FastFormatter>
				<FastFormatter _type="null" condition="b,U,g,0,i" description="info=b,U,g,0,i" format="Username: &quot;$10&quot;, AuthID: &quot;$13&quot;, Type: Binary, Action: Not Compressed, Mode: Guest, Auth_Used: None, Status: Incomplete" matcherInput="$6,$7,$9,$12,$14" version="1" version_type="int"></FastFormatter>
				<FastFormatter _type="null" condition="b,U,g,1,c" description="info=b,U,g,1,c" format="Username: &quot;$10&quot;, AuthID: &quot;$13&quot;, Type: Binary, Action: Not Compressed, Mode: Guest, Auth_Used: RFC931, Status: Complete" matcherInput="$6,$7,$9,$12,$14" version="1" version_type="int"></FastFormatter>
				<FastFormatter _type="null" condition="b,U,g,1,i" description="info=b,U,g,1,i" format="Username: &quot;$10&quot;, AuthID: &quot;$13&quot;, Type: Binary, Action: Not Compressed, Mode: Guest, Auth_Used: RFC931, Status: Incomplete" matcherInput="$6,$7,$9,$12,$14" version="1" version_type="int"></FastFormatter>
				<FastFormatter _type="null" condition="b,U,r,0,c" description="info=b,U,r,0,c" format="Username: &quot;$10&quot;, AuthID: &quot;$13&quot;, Type: Binary, Action: Not Compressed, Mode: Local, Auth_Used: None, Status: Complete" matcherInput="$6,$7,$9,$12,$14" version="1" version_type="int"></FastFormatter>
				<FastFormatter _type="null" condition="b,U,r,0,i" description="info=b,U,r,0,i" format="Username: &quot;$10&quot;, AuthID: &quot;$13&quot;, Type: Binary, Action: Not Compressed, Mode: Local, Auth_Used: None, Status: Incomplete" matcherInput="$6,$7,$9,$12,$14" version="1" version_type="int"></FastFormatter>
				<FastFormatter _type="null" condition="b,U,r,1,c" description="info=b,U,r,1,c" format="Username: &quot;$10&quot;, AuthID: &quot;$13&quot;, Type: Binary, Action: Not Compressed, Mode: Local, Auth_Used: RFC931, Status: Complete" matcherInput="$6,$7,$9,$12,$14" version="1" version_type="int"></FastFormatter>
				<FastFormatter _type="null" condition="b,U,r,1,i" description="info=b,U,r,1,i" format="Username: &quot;$10&quot;, AuthID: &quot;$13&quot;, Type: Binary, Action: Not Compressed, Mode: Local, Auth_Used: RFC931, Status: Incomplete" matcherInput="$6,$7,$9,$12,$14" version="1" version_type="int"></FastFormatter>
			</FastField>
			<FastField _type="null" defaultValue="" fieldName="SourceMachine" type="1" type_type="int" version="1" version_type="int">
				<FastFormatter _type="null" condition="i" description="incoming" format="$3" matcherInput="$8" version="1" version_type="int"></FastFormatter>
			</FastField>
			<FastField _type="null" defaultValue="" fieldName="DestinationMachine" type="1" type_type="int" version="2" version_type="int">
				<FastFormatter _type="null" condition="o" description="outgoing" format="$3" matcherInput="$8" version="1" version_type="int"></FastFormatter>
			</FastField>
			<FastField _type="null" defaultValue="$11" fieldName="Protocol" type="1" type_type="int" version="1" version_type="int"></FastField>
		</FastPattern>
		<FastPattern _type="null" alertName="InternalNewToolData" description="InternalNewToolData: unmatched data" matcher="\w{3} (\w{3} +\d{1,2} \d{2}:\d{2}:\d{2} \d{4}).*" pattern="\w{3} \w{3} +\d{1,2} \d{2}:\d{2}:\d{2} \d{4} \d+ [-\w.]+ \d+ .+ \w \w \w \w \S+ [-\w]+ \d+ \S+ \w.*" version="1" version_type="int">
			<FastField _type="null" defaultValue="Unmatched vsftp data ($Revision: #4 $)" fieldName="EventInfo" type="1" type_type="int" version="1" version_type="int"></FastField>
			<FastField _type="null" defaultValue="" fieldName="DetectionTime" type="4" type_type="int" version="1" version_type="int">
				<FastFormatter _type="null" condition="Jan (\d{2}) (\d{2}:\d{2}:\d{2}) (\d{4})" description="2day-Jan" format="$18-01-$16 $17" matcherInput="$1" version="1" version_type="int"></FastFormatter>
				<FastFormatter _type="null" condition="Feb (\d{2}) (\d{2}:\d{2}:\d{2}) (\d{4})" description="2day-Feb" format="$18-02-$16 $17" matcherInput="$1" version="1" version_type="int"></FastFormatter>
				<FastFormatter _type="null" condition="Mar (\d{2}) (\d{2}:\d{2}:\d{2}) (\d{4})" description="2day-Mar" format="$18-03-$16 $17" matcherInput="$1" version="1" version_type="int"></FastFormatter>
				<FastFormatter _type="null" condition="Apr (\d{2}) (\d{2}:\d{2}:\d{2}) (\d{4})" description="2day-Apr" format="$18-04-$16 $17" matcherInput="$1" version="1" version_type="int"></FastFormatter>
				<FastFormatter _type="null" condition="May (\d{2}) (\d{2}:\d{2}:\d{2}) (\d{4})" description="2day-May" format="$18-05-$16 $17" matcherInput="$1" version="1" version_type="int"></FastFormatter>
				<FastFormatter _type="null" condition="Jun (\d{2}) (\d{2}:\d{2}:\d{2}) (\d{4})" description="2day-Jun" format="$18-06-$16 $17" matcherInput="$1" version="1" version_type="int"></FastFormatter>
				<FastFormatter _type="null" condition="Jul (\d{2}) (\d{2}:\d{2}:\d{2}) (\d{4})" description="2day-Jul" format="$18-07-$16 $17" matcherInput="$1" version="1" version_type="int"></FastFormatter>
				<FastFormatter _type="null" condition="Aug (\d{2}) (\d{2}:\d{2}:\d{2}) (\d{4})" description="2day-Aug" format="$18-08-$16 $17" matcherInput="$1" version="1" version_type="int"></FastFormatter>
				<FastFormatter _type="null" condition="Sep (\d{2}) (\d{2}:\d{2}:\d{2}) (\d{4})" description="2day-Sep" format="$18-09-$16 $17" matcherInput="$1" version="1" version_type="int"></FastFormatter>
				<FastFormatter _type="null" condition="Oct (\d{2}) (\d{2}:\d{2}:\d{2}) (\d{4})" description="2day-Oct" format="$18-10-$16 $17" matcherInput="$1" version="1" version_type="int"></FastFormatter>
				<FastFormatter _type="null" condition="Nov (\d{2}) (\d{2}:\d{2}:\d{2}) (\d{4})" description="2day-Nov" format="$18-11-$16 $17" matcherInput="$1" version="1" version_type="int"></FastFormatter>
				<FastFormatter _type="null" condition="Dec (\d{2}) (\d{2}:\d{2}:\d{2}) (\d{4})" description="2day-Dec" format="$18-12-$16 $17" matcherInput="$1" version="1" version_type="int"></FastFormatter>
				<FastFormatter _type="null" condition="Jan +(\d) (\d{2}:\d{2}:\d{2}) (\d{4})" description="1day-Jan" format="$18-01-0$16 $17" matcherInput="$1" version="1" version_type="int"></FastFormatter>
				<FastFormatter _type="null" condition="Feb +(\d) (\d{2}:\d{2}:\d{2}) (\d{4})" description="1day-Feb" format="$18-02-0$16 $17" matcherInput="$1" version="1" version_type="int"></FastFormatter>
				<FastFormatter _type="null" condition="Mar +(\d) (\d{2}:\d{2}:\d{2}) (\d{4})" description="1day-Mar" format="$18-03-0$16 $17" matcherInput="$1" version="1" version_type="int"></FastFormatter>
				<FastFormatter _type="null" condition="Apr +(\d) (\d{2}:\d{2}:\d{2}) (\d{4})" description="1day-Apr" format="$18-04-0$16 $17" matcherInput="$1" version="1" version_type="int"></FastFormatter>
				<FastFormatter _type="null" condition="May +(\d) (\d{2}:\d{2}:\d{2}) (\d{4})" description="1day-May" format="$18-05-0$16 $17" matcherInput="$1" version="1" version_type="int"></FastFormatter>
				<FastFormatter _type="null" condition="Jun +(\d) (\d{2}:\d{2}:\d{2}) (\d{4})" description="1day-Jun" format="$18-06-0$16 $17" matcherInput="$1" version="1" version_type="int"></FastFormatter>
				<FastFormatter _type="null" condition="Jul +(\d) (\d{2}:\d{2}:\d{2}) (\d{4})" description="1day-Jul" format="$18-07-0$16 $17" matcherInput="$1" version="1" version_type="int"></FastFormatter>
				<FastFormatter _type="null" condition="Aug +(\d) (\d{2}:\d{2}:\d{2}) (\d{4})" description="1day-Aug" format="$18-08-0$16 $17" matcherInput="$1" version="1" version_type="int"></FastFormatter>
				<FastFormatter _type="null" condition="Sep +(\d) (\d{2}:\d{2}:\d{2}) (\d{4})" description="1day-Sep" format="$18-09-0$16 $17" matcherInput="$1" version="1" version_type="int"></FastFormatter>
				<FastFormatter _type="null" condition="Oct +(\d) (\d{2}:\d{2}:\d{2}) (\d{4})" description="1day-Oct" format="$18-10-0$16 $17" matcherInput="$1" version="1" version_type="int"></FastFormatter>
				<FastFormatter _type="null" condition="Nov +(\d) (\d{2}:\d{2}:\d{2}) (\d{4})" description="1day-Nov" format="$18-11-0$16 $17" matcherInput="$1" version="1" version_type="int"></FastFormatter>
				<FastFormatter _type="null" condition="Dec +(\d) (\d{2}:\d{2}:\d{2}) (\d{4})" description="1day-Dec" format="$18-12-0$16 $17" matcherInput="$1" version="1" version_type="int"></FastFormatter>
			</FastField>
			<FastField _type="null" defaultValue="$0" fieldName="ExtraneousInfo" type="1" type_type="int" version="1" version_type="int"></FastField>
		</FastPattern>
		<FastPattern _type="null" alertName="" alertName_type="null" description="NullAlert: black hole" matcher=".*" pattern=".*" version="1" version_type="int"></FastPattern>
	</FastToolId>
</FASTConfiguration>
